[
  {
    "id": "1",
    "name": "Іван",
    "email": "ivan@example.com",
    "age": "22"
  },
  {
    "id": "2",
    "name": "Марія",
    "email": "maria@example.com",
    "age": "22"
  },
  {
    "id": "3",
    "name": "Петро",
    "email": "petro@example.com",
    "age": "22"
  },
  {
    "id": "4",
    "name": "Ольга",
    "email": "olga@example.com",
    "age": "22"
  },
  {
    "id": "5",
    "name": "Андрій",
    "email": "andriy@example.com",
    "age": "22"
  },
  {
    "id": "6",
    "name": "Наталія",
    "email": "natalia@example.com",
    "age": "22"
  },
  {
    "id": "7",
    "name": "Максим",
    "email": "maxim@example.com",
    "age": "22"
  },
  {
    "id": "8",
    "name": "Софія",
    "email": "sofia@example.com",
    "age": "22"
  },
  {
    "id": "9",
    "name": "Анна",
    "email": "anna@example.com",
    "age": "22"
  },
  {
    "id": "11",
    "name": "Alex-4",
    "email": "alex@example.com",
    "age": "52"
  }
]